<annotation>
  <folder>sano</folder>
  <filename>849aa978-c7b9-4344-9ca8-129219a65f8e___RS_HL 1874</filename>
  <path>C:\Users\julia\Desktop\TESIS_A\INTENTO_2\dataset\sano\849aa978-c7b9-4344-9ca8-129219a65f8e___RS_HL 1874.JPG</path>
  <source>
    <database>Unknown</database>
  </source>
  <size>
    <width>256</width>
    <height>256</height>
    <depth>3</depth>
  </size>
  <segmented>0</segmented>
  <object>
    <name>sano</name>
    <pose>Unspecified</pose>
    <truncated>0</truncated>
    <difficult>0</difficult>
    <bndbox>
      <xmin>5</xmin>
      <ymin>6</ymin>
      <xmax>239</xmax>
      <ymax>239</ymax>
    </bndbox>
  </object>
</annotation>
